Metadata-Version: 1.0
Name: mlf-distributions
Version: 0.1
Summary: Gaussian and Binomial distributions
Home-page: UNKNOWN
Author: Chin-Wu Chen
Author-email: cwchen1976@gmail.com
License: UNKNOWN
Platform: UNKNOWN
